jwt_library/__init__.py
jwt_library/decorators/__init__.py
jwt_library/decorators/auth0_decorators.py
jwt_library/decorators/decorators.py
jwt_library/jwt_operations/__init__.py
jwt_library/jwt_operations/auth0/__init__.py
jwt_library/jwt_operations/auth0/jwt_operations.py
jwt_library/jwt_operations/utils/__init__.py
jwt_library/jwt_operations/utils/errors/__init__.py
jwt_library/jwt_operations/utils/errors/auth_errors.py
jwt_library/jwt_operations/utils/token_validation/__init__.py
contractor_jwt_lib-0.0.16.dist-info/LICENSE
contractor_jwt_lib-0.0.16.dist-info/METADATA
contractor_jwt_lib-0.0.16.dist-info/WHEEL
contractor_jwt_lib-0.0.16.dist-info/top_level.txt
contractor_jwt_lib-0.0.16.dist-info/RECORD
